zato_enclog-1.0.7-py2.7-nspkg.pth
zato_enclog-1.0.7.dist-info/METADATA
zato_enclog-1.0.7.dist-info/top_level.txt
zato_enclog-1.0.7.dist-info/DESCRIPTION.rst
zato_enclog-1.0.7.dist-info/RECORD
zato_enclog-1.0.7.dist-info/WHEEL
zato_enclog-1.0.7.dist-info/namespace_packages.txt
zato_enclog-1.0.7.dist-info/metadata.json
zato/enclog/__init__.py
zato/enclog/_core.py
zato_enclog-1.0.7.data/scripts/enclog
