Metadata-Version: 2.0
Name: zato-enclog
Version: 1.0.7
Summary: Encrypted logger reusable in any Python application
Home-page: https://zato.io/docs/progguide/enclog/index.html
Author: Zato Source s.r.o.
Author-email: enclog@m.zato.io
License: BSD License
Platform: OS Independent
Classifier: Development Status :: 5 - Production/Stable
Classifier: Environment :: Console
Classifier: Environment :: Web Environment
Classifier: Intended Audience :: Developers
Classifier: Intended Audience :: Information Technology
Classifier: Intended Audience :: Other Audience
Classifier: License :: OSI Approved :: BSD License
Classifier: Natural Language :: English
Classifier: Operating System :: OS Independent
Classifier: Programming Language :: Python
Classifier: Programming Language :: Python :: 2
Classifier: Programming Language :: Python :: 3
Classifier: Intended Audience :: Developers
Classifier: Topic :: Communications
Classifier: Topic :: Education :: Testing
Classifier: Topic :: Internet
Classifier: Topic :: Internet :: Proxy Servers
Classifier: Topic :: Internet :: WWW/HTTP
Classifier: Topic :: Security
Classifier: Topic :: System :: Networking
Classifier: Topic :: Utilities
Requires-Dist: bunch (>=1.0.1)
Requires-Dist: click (>=6.2)
Requires-Dist: coverage (>=3.7.1)
Requires-Dist: cryptography (>=1.1.1)
Requires-Dist: flake8 (>=2.1.0)
Requires-Dist: future (>=0.15.2)
Requires-Dist: nose (>=1.3.3)
Requires-Dist: tailer (>=0.4)
Requires-Dist: testfixtures (>=4.6.0)
